connectedpapersextractor/Config.py
connectedpapersextractor/__init__.py
connectedpapersextractor/article.py
connectedpapersextractor/create_related_work.py
connectedpapersextractor/get_summaries_from_arxiv.py
connectedpapersextractor/get_summaries_from_connected_papers.py
connectedpapersextractor/services/__init__.py
connectedpapersextractor/services/article_filter.py
connectedpapersextractor/services/convert_service.py
connectedpapersextractor/services/main_parts_extractor.py
connectedpapersextractor/services/sumaries_combine.py
connectedpapersextractor/services/summarizer.py
connectedpapersextractor/services/text_splitter.py
connectedpapersextractor/utils/__init__.py
connectedpapersextractor/utils/download_summaries.py
connectedpapersextractor/utils/download_summaries_from_arxiv.py
connectedpapersextractor/utils/download_summaries_from_connected_papers.py
connectedpapersextractor/utils/get_existing_summaries.py
connectedpapersextractor/utils/summarize_documents.py
connectedpapersextractor-0.2.1.dist-info/LICENSE
connectedpapersextractor-0.2.1.dist-info/METADATA
connectedpapersextractor-0.2.1.dist-info/WHEEL
connectedpapersextractor-0.2.1.dist-info/RECORD
