Metadata-Version: 2.1
Name: ConnectedPapersExtractor
Version: 0.2.1
Summary: A package for creating summaries based on https://www.connectedpapers.com/.
License: MIT
Author: Tesla2000
Author-email: fratajczak124@gmail.com
Requires-Python: >=3.8.1,<4.0.0
Classifier: License :: OSI Approved :: MIT License
Classifier: Programming Language :: Python :: 3
Classifier: Programming Language :: Python :: 3.9
Classifier: Programming Language :: Python :: 3.10
Classifier: Programming Language :: Python :: 3.11
Classifier: Programming Language :: Python :: 3.12
Requires-Dist: EnhancedWebdriver (>=0.1.6,<0.2.0)
Requires-Dist: PyPDF2 (>=3.0.1,<4.0.0)
Requires-Dist: arxiv (>=2.1.0,<3.0.0)
Requires-Dist: cffi (>=1.16.0,<2.0.0)
Requires-Dist: chromedriver-autoinstaller (>=0.6.4,<0.7.0)
Requires-Dist: download (>=0.3.5,<0.4.0)
Requires-Dist: injector (>=0.21.0,<0.22.0)
Requires-Dist: langchain (>=0.1.16,<0.2.0)
Requires-Dist: langchain-experimental (>=0.0.57,<0.0.58)
Requires-Dist: langchain-openai (>=0.1.4,<0.2.0)
Requires-Dist: pypdf (>=4.2.0,<5.0.0)
Requires-Dist: python-dotenv (>=1.0.1,<2.0.0)
Requires-Dist: undetected-chromedriver (>=3.5.5,<4.0.0)
